fusionsid/__init__.py
fusionsid/__main__.py
fusionsid/decorators.py
fusionsid/errors.py
fusionsid/filter.py
fusionsid/fun.py
fusionsid/http.py
fusionsid/image.py
fusionsid/text.py
fusionsidsapi-1.0.6.dist-info/LICENCE
fusionsidsapi-1.0.6.dist-info/METADATA
fusionsidsapi-1.0.6.dist-info/WHEEL
fusionsidsapi-1.0.6.dist-info/entry_points.txt
fusionsidsapi-1.0.6.dist-info/top_level.txt
fusionsidsapi-1.0.6.dist-info/RECORD
