Metadata-Version: 2.1
Name: fusionsidsapi
Version: 1.0.6
Summary: An asynchronous api wrapper for FusionSidsAPI.
Home-page: https://github.com/FusionSid/FusionSidAPI.py
Author: FusionSid
Author-email: siddheshadsv@icloud.com
License: UNKNOWN
Platform: UNKNOWN
License-File: LICENCE
Requires-Dist: aiofiles (==0.6.0)
Requires-Dist: aiohttp (==3.8.1)
Requires-Dist: Pillow (==9.1.0)
Requires-Dist: rich (==12.2.0)
